{
    "type":"kart_bot",
    "setup":
        {
            "model":"retro_car_red",
            "frameRate":30,
            "rotationOrder":"XZY",
            "scale":{"x":5000,"y":5000,"z":5000},
            "radius":5000,
            "height":5000,
            "eyeOffset":4800,
            "weight":500,
            "hideMeshes":[]
        },
    "config":
        {
            "maxTurnSpeed":"@turnSpeed",
            "driftMaxTurnSpeed":2.5,
            "forwardAcceleration":8,
            "forwardDeceleration":25,
            "forwardMaxSpeed":"@speed",
            "reverseAcceleration":5,
            "reverseDeceleration":35,
            "reverseMaxSpeed":1000,
            "forwardBrakeDeceleration":50,
            "reverseBrakeDeceleration":50,
            "jumpHeight":1000,
            "bounceWaitCount":20,
            "spinOutSpeed":6,
            "driftDecelerationFactor":0.99,
            "targetScanYRange":30,
            "maxFireDistance":60000,
            "minFireDistance":15000,
            "fireWaitTick":5000,
            "maxSpeedItemCount":10,
            "speedItemIncrease":10,
            "rigidBodyMaxDrop":3000,
            "rigidBodyMaxAngle":25,
            "rigidBodyTransformPerTick":0.025,
            "engineSoundRateMin":0.5,
            "engineSoundRateAdd":0.8,
            "engineSoundRateAirIncrease":0.2,
            "smokeThickness":2,
            "smokeAngles":[135,225],
            "smokeEffect":"tire_smoke",
            "burstThickness":1,
            "burstAngles":[135,225],
            "burstEffect":"exhaust",
            "pathNodeSlop":8000,
            "driftMinAngle":60,
            "brakeMinAngle":90,
            "turnCoolDownPeriod":15
        },
    "animations":
        {
            "idleAnimation":[175,275],
            "driveAnimation":[380,400],
            "turnLeftAnimation":[405,425],
            "turnRightAnimation":[435,455],
            "spinOutAnimation":[275,375]
        },
    "sounds":
        {
            "engineSound":{"name":"engine","rate":0.5,"randomRateAdd":0,"distance":80000,"loopStart":0,"loopEnd":3.0,"loop":true},
            "skidSound":{"name":"skid","rate":1.0,"randomRateAdd":0,"distance":80000,"loopStart":0,"loopEnd":0,"loop":false},
            "burstSound":{"name":"burst","rate":1.0,"randomRateAdd":0,"distance":50000,"loopStart":0,"loopEnd":0,"loop":false},
            "crashKartSound":{"name":"crash","rate":1.0,"randomRateAdd":0.2,"distance":100000,"loopStart":0,"loopEnd":0,"loop":false},
            "crashWallSound":{"name":"crash","rate":0.8,"randomRateAdd":0.2,"distance":100000,"loopStart":0,"loopEnd":0,"loop":false}
        },
    "weapons":
        [
            {
                "weaponJson":"weapon_bowling_ball",
                "weaponData":null,
                "name":"weapon_bowling_ball",
                "parentIdleAnimation":[0,0],
                "parentRunAnimation":[0,0],
                "parentFireIdleAnimation":[0,0],
                "parentPrimaryFireRunAnimation":[0,0],
                "parentSecondaryFireRunAnimation":[0,0],
                "parentTertiaryFireRunAnimation":[0,0],
                "meshes":[]
            }
        ]
}
