{
    "type":"projectile",
    "setup":
        {
            "model":"bowling_ball",
            "frameRate":30,
            "rotationOrder":"XYZ",
            "scale":{"x":2000,"y":2000,"z":2000},
            "radius":1000,
            "height":1000,
            "eyeOffset":0,
            "weight":100,
            "hideMeshes":[]
        },
    "config":
        {
            "lifeTick":4000,
            "speed":2200,
            "damage":1,
            "floats":false,
            "followsFloor":true,
            "spins":false,
            "spinRate":0,
            "tumbles":false,
            "stopOnHit":true,
            "canRoll":true,
            "rollDeceleration":1.0,
            "canBounce":false,
            "bounceFactor":0,
            "canReflect":true,
            "trackList":["kart_player","kart_bot"],
            "trackSpeed":4,
            "hitEffect":"explosion",
            "trailEffect":"exhaust",
            "trailSpawnTick":20
        },
    "sounds":
        {
            "bounceSound":null,
            "reflectSound":null,
            "spawnSound":null
        }
}
